rcctl/__init__.py
rcctl/apiclient.py
rcctl/auth.py
rcctl/commands.py
rcctl/config.py
rcctl/custom_cluster.py
rcctl/custom_reliablecollections.py
rcctl/entry.py
rcctl/helps/__init__.py
rcctl/helps/main.py
rcctl-1.2.0.dist-info/METADATA
rcctl-1.2.0.dist-info/RECORD
rcctl-1.2.0.dist-info/WHEEL
rcctl-1.2.0.dist-info/entry_points.txt
rcctl-1.2.0.dist-info/top_level.txt
